jd_union/__init__.py
jd_union/api/__init__.py
jd_union/api/base.py
jd_union/api/rest/CreatePromotionSiteJosSaveAppPromtionSiteInfoRequest.py
jd_union/api/rest/ServiceCouponImportCouponRequest.py
jd_union/api/rest/ServiceGoodsQuerySecKillGoodsRequest.py
jd_union/api/rest/ServiceGoodsQueryStuPriceGoodsRequest.py
jd_union/api/rest/ServicePromotionAppGetcodeRequest.py
jd_union/api/rest/ServicePromotionAppReportRequest.py
jd_union/api/rest/ServicePromotionBatchGetcodeRequest.py
jd_union/api/rest/ServicePromotionContentGetcodeRequest.py
jd_union/api/rest/ServicePromotionCouponGetCodeBySubUnionIdRequest.py
jd_union/api/rest/ServicePromotionCouponGetCodeByUnionIdRequest.py
jd_union/api/rest/ServicePromotionCouponGetInfoRequest.py
jd_union/api/rest/ServicePromotionCreatePromotionSiteBatchRequest.py
jd_union/api/rest/ServicePromotionGetcodeRequest.py
jd_union/api/rest/ServicePromotionGoodsInfoRequest.py
jd_union/api/rest/ServicePromotionPidGetPidRequest.py
jd_union/api/rest/ServicePromotionQueryDesignboomGoodsRequest.py
jd_union/api/rest/ServicePromotionQueryPromotionSiteRequest.py
jd_union/api/rest/ServicePromotionWxsqGetCodeBySubUnionIdRequest.py
jd_union/api/rest/ServicePromotionWxsqGetCodeByUnionIdRequest.py
jd_union/api/rest/ServiceYhdPromotionGetInfoRequest.py
jd_union/api/rest/UnionDoubanBookServiceQueryBookUrlListRequest.py
jd_union/api/rest/UnionOrderServiceQueryCommisionsRequest.py
jd_union/api/rest/UnionSearchGoodsCategoryQueryRequest.py
jd_union/api/rest/UnionSearchGoodsKeywordQueryRequest.py
jd_union/api/rest/UnionSearchGoodsParamQueryRequest.py
jd_union/api/rest/UnionSearchQueryCouponGoodsRequest.py
jd_union/api/rest/UnionServiceQueryCommissionOrdersRequest.py
jd_union/api/rest/UnionServiceQueryCommissionOrdersWithKeyRequest.py
jd_union/api/rest/UnionServiceQueryImportOrdersRequest.py
jd_union/api/rest/UnionServiceQueryImportOrdersWithKeyRequest.py
jd_union/api/rest/UnionServiceQueryOrderListRequest.py
jd_union-18.12.8.18.dist-info/DESCRIPTION.rst
jd_union-18.12.8.18.dist-info/METADATA
jd_union-18.12.8.18.dist-info/RECORD
jd_union-18.12.8.18.dist-info/WHEEL
jd_union-18.12.8.18.dist-info/metadata.json
jd_union-18.12.8.18.dist-info/top_level.txt
