Metadata-Version: 2.0
Name: jd-union
Version: 18.12.8.18
Summary: 京东联盟 sdk
Home-page: UNKNOWN
Author: play4fun
Author-email: play4fun@foxmail.com
License: MIT
Platform: UNKNOWN
